shapenet/__init__.py
shapenet/jit/__init__.py
shapenet/jit/abstract_network.py
shapenet/jit/feature_extractors.py
shapenet/jit/homogeneous_shape_layer.py
shapenet/jit/homogeneous_transform_layer.py
shapenet/jit/shape_layer.py
shapenet/jit/shape_network.py
shapenet/layer/__init__.py
shapenet/layer/homogeneous_shape_layer.py
shapenet/layer/homogeneous_transform_layer.py
shapenet/layer/shape_layer.py
shapenet/networks/__init__.py
shapenet/networks/abstract_network.py
shapenet/networks/feature_extractors.py
shapenet/networks/utils.py
shapenet/networks/single_shape/__init__.py
shapenet/networks/single_shape/shape_network.py
shapenet/scripts/__init__.py
shapenet/scripts/export_to_jit.py
shapenet/scripts/predict_from_net.py
shapenet/scripts/prepare_datasets.py
shapenet/scripts/train_single_shapenet.py
shapenet/utils/__init__.py
shapenet/utils/load_config_file.py
shapenet/utils/misc.py
tests/__init__.py
tests/jit/__init__.py
tests/jit/test_jit_equality.py
tests/layer/__init__.py
tests/layer/test_homogeneous_shape_layer.py
tests/layer/test_homogeneous_transform_layer.py
tests/networks/__init__.py
tests/networks/test_feature_extractor.py
tests/networks/test_single_shape_network.py
tests/utils/__init__.py
tests/utils/test_config.py
shapenet-0.1.0.dist-info/LICENSE
shapenet-0.1.0.dist-info/METADATA
shapenet-0.1.0.dist-info/WHEEL
shapenet-0.1.0.dist-info/top_level.txt
shapenet-0.1.0.dist-info/RECORD
